crypto_crawler/__init__.py
crypto_crawler/_lowlevel.py
crypto_crawler/_lowlevel__ffi.py
crypto_crawler/_lowlevel__lib.so
crypto_crawler-3.2.6.dist-info/LICENSE
crypto_crawler-3.2.6.dist-info/METADATA
crypto_crawler-3.2.6.dist-info/WHEEL
crypto_crawler-3.2.6.dist-info/top_level.txt
crypto_crawler-3.2.6.dist-info/RECORD
