Metadata-Version: 2.1
Name: crypto-crawler
Version: 3.2.6
Summary: A rock-solid cryprocurrency crawler
Home-page: https://github.com/soulmachine/crypto-crawler-py
Author: soulmachine
License: UNKNOWN
Keywords: blockchain,cryptocurrency,trading
Platform: UNKNOWN
Classifier: Programming Language :: Python :: 3.6
Classifier: License :: OSI Approved :: Apache Software License
Classifier: Topic :: Software Development :: Libraries :: Python Modules
Requires-Python: >=3.6
Requires-Dist: milksnake
